autopep723/__init__.py
autopep723/cli.py
autopep723/commands.py
autopep723/logger.py
autopep723/validation.py
autopep723-0.2.0.dist-info/WHEEL
autopep723-0.2.0.dist-info/entry_points.txt
autopep723-0.2.0.dist-info/METADATA
autopep723-0.2.0.dist-info/RECORD
