Metadata-Version: 2.4
Name: autopep723
Version: 0.2.0
Summary: Auto-generate PEP 723 metadata for Python scripts by analyzing imports
Author: Martín Gaitán
Author-email: Martín Gaitán <gaitan@gmail.com>
License-Expression: MIT
Requires-Python: >=3.9
